{
  "info": {
    "name": "Fandit Zoo API",
    "_postman_id": "f3c8c85c-2c44-4a6f-9a6a-1234567890ab",
    "description": "Colección de Postman para probar la API REST de gestión de zoológicos con flujo automático usando variable de entorno zoo_id.",
    "schema": "https://schema.getpostman.com/json/collection/v2.1.0/collection.json"
  },
  "item": [
    {
      "name": "Zoos",
      "item": [
        {
          "name": "Listar Zoos",
          "request": {
            "method": "GET",
            "header": [],
            "url": {
              "raw": "http://127.0.0.1:8000/",
              "protocol": "http",
              "host": ["127.0.0.1"],
              "port": "8000",
              "path": []
            },
            "description": "Devuelve todos los zoológicos con detalles: ID, nombre, ciudad, país, tamaño, presupuesto, cantidad de animales y animales agrupados por familia."
          }
        },
        {
          "name": "Crear Zoo",
          "request": {
            "method": "POST",
            "header": [
              {
                "key": "Content-Type",
                "value": "application/json"
              }
            ],
            "body": {
              "mode": "raw",
              "raw": "{\n  \"name\": \"Zoo de Prueba\",\n  \"city\": \"Ciudad\",\n  \"country\": \"País\",\n  \"size_m2\": 50000,\n  \"annual_budget\": 3000000,\n  \"animals\": [\"Panthera tigris\", \"Ailuropoda melanoleuca\"]\n}"
            },
            "url": {
              "raw": "http://127.0.0.1:8000/create/",
              "protocol": "http",
              "host": ["127.0.0.1"],
              "port": "8000",
              "path": ["create", ""]
            },
            "description": "Crea un nuevo zoológico. Los animales se pasan mediante nombre científico."
          },
          "event": [
            {
              "listen": "test",
              "script": {
                "exec": [
                  "let data = pm.response.json();",
                  "if (data.id) {",
                  "    pm.environment.set('zoo_id', data.id);",
                  "}"
                ],
                "type": "text/javascript"
              }
            }
          ]
        },
        {
          "name": "Actualizar Zoo",
          "request": {
            "method": "POST",
            "header": [
              {
                "key": "Content-Type",
                "value": "application/json"
              }
            ],
            "body": {
              "mode": "raw",
              "raw": "{\n  \"name\": \"Zoo Editado\",\n  \"city\": \"Ciudad Editada\",\n  \"country\": \"País Editado\",\n  \"size_m2\": 60000,\n  \"annual_budget\": 3500000,\n  \"animals\": [\"Panthera tigris\", \"Canis lupus\"]\n}"
            },
            "url": {
              "raw": "http://127.0.0.1:8000/{{zoo_id}}/edit/",
              "protocol": "http",
              "host": ["127.0.0.1"],
              "port": "8000",
              "path": ["{{zoo_id}}", "edit", ""]
            },
            "description": "Actualiza el zoológico recién creado usando la variable de entorno zoo_id y nombres científicos de animales."
          }
        },
        {
          "name": "Eliminar Zoo",
          "request": {
            "method": "DELETE",
            "url": {
              "raw": "http://127.0.0.1:8000/{{zoo_id}}/delete/",
              "protocol": "http",
              "host": ["127.0.0.1"],
              "port": "8000",
              "path": ["{{zoo_id}}", "delete", ""]
            },
            "description": "Elimina el zoológico recién creado usando la variable de entorno zoo_id."
          }
        }
      ]
    }
  ]
}

